canvasapiutils/__init__.py
canvasapiutils-0.1.0.dist-info/licenses/LICENSE
canvasapiutils-0.1.0.dist-info/METADATA
canvasapiutils-0.1.0.dist-info/WHEEL
canvasapiutils-0.1.0.dist-info/top_level.txt
canvasapiutils-0.1.0.dist-info/RECORD
